quant_proto/__init__.py
quant_proto/quant.proto
quant_proto/quant_pb2.py
quant_proto/quant_pb2_grpc.py
quant_proto/servicer.py
tests/__init__.py
tests/test_quant_proto.py
quant_proto-0.1.0.dist-info/METADATA
quant_proto-0.1.0.dist-info/WHEEL
quant_proto-0.1.0.dist-info/top_level.txt
quant_proto-0.1.0.dist-info/RECORD
