Metadata-Version: 2.1
Name: quant-proto
Version: 0.1.0
Summary: Protobuf definitions for Quant services
Author: AnthroSpark
Author-email: admin@anthrospark.com
Classifier: Programming Language :: Python :: 3
Classifier: License :: OSI Approved :: MIT License
Requires-Dist: protobuf ==4.24.3
Requires-Dist: grpcio ==1.58.0
